{
    "en": [
        {"city": "Athens", "region": "Attica"},
        {"city": "Thessaloniki", "region": "Central Macedonia"},
        {"city": "Patras", "region": "Western Greece"},
        {"city": "Piraeus", "region": "Attica"},
        {"city": "Larissa", "region": "Thessaly"},
        {"city": "Heraklion", "region": "Crete"},
        {"city": "Peristeri", "region": "Attica"},
        {"city": "Kallithea", "region": "Attica"},
        {"city": "Acharnes", "region": "Attica"},
        {"city": "Kalamaria", "region": "Central Macedonia"},
        {"city": "Nikaia", "region": "Attica"},
        {"city": "Glyfada", "region": "Attica"},
        {"city": "Volos", "region": "Thessaly"},
        {"city": "Ilio", "region": "Attica"},
        {"city": "Ilioupoli", "region": "Attica"},
        {"city": "Keratsini", "region": "Attica"},
        {"city": "Evosmos", "region": "Central Macedonia"},
        {"city": "Chalandri", "region": "Attica"},
        {"city": "Nea Smyrni", "region": "Attica"},
        {"city": "Marousi", "region": "Attica"},
        {"city": "Agios Dimitrios", "region": "Attica"},
        {"city": "Zografou", "region": "Attica"},
        {"city": "Egaleo", "region": "Attica"},
        {"city": "Nea Ionia", "region": "Attica"},
        {"city": "Ioannina", "region": "Epirus"},
        {"city": "Palaio Faliro", "region": "Attica"},
        {"city": "Korydallos", "region": "Attica"},
        {"city": "Trikala", "region": "Thessaly"},
        {"city": "Vyronas", "region": "Attica"},
        {"city": "Agia Paraskevi", "region": "Attica"},
        {"city": "Galatsi", "region": "Attica"},
        {"city": "Agrinio", "region": "Western Greece"},
        {"city": "Chalcis", "region": "Central Greece"},
        {"city": "Petroupoli", "region": "Attica"},
        {"city": "Serres", "region": "Central Macedonia"},
        {"city": "Alexandroupoli", "region": "Eastern Macedonia and Thrace"},
        {"city": "Xanthi", "region": "Eastern Macedonia and Thrace"},
        {"city": "Katerini", "region": "Central Macedonia"},
        {"city": "Kalamata", "region": "Peloponnese"},
        {"city": "Kavala", "region": "Eastern Macedonia and Thrace"},
        {"city": "Chania", "region": "Crete"},
        {"city": "Lamia", "region": "Central Greece"},
        {"city": "Komotini", "region": "Eastern Macedonia and Thrace"},
        {"city": "Irakleio", "region": "Attica"},
        {"city": "Rhodes", "region": "South Aegean"},
        {"city": "Kifissia", "region": "Attica"},
        {"city": "Stavroupoli", "region": "Central Macedonia"},
        {"city": "Chaidari", "region": "Attica"},
        {"city": "Drama", "region": "Eastern Macedonia and Thrace"},
        {"city": "Veria", "region": "Central Macedonia"},
        {"city": "Alimos", "region": "Attica"},
        {"city": "Kozani", "region": "Western Macedonia"},
        {"city": "Polichni", "region": "Central Macedonia"},
        {"city": "Karditsa", "region": "Thessaly"},
        {"city": "Sykies", "region": "Central Macedonia"},
        {"city": "Ampelokipoi", "region": "Central Macedonia"},
        {"city": "Pylaia", "region": "Central Macedonia"},
        {"city": "Agioi Anargyroi", "region": "Attica"},
        {"city": "Ano Liosia", "region": "Attica"},
        {"city": "Nea Ionia", "region": "Thessaly"},
        {"city": "Rethymno", "region": "Crete"},
        {"city": "Ptolemaida", "region": "Western Macedonia"},
        {"city": "Tripoli", "region": "Peloponnese"},
        {"city": "Cholargos", "region": "Attica"},
        {"city": "Vrilissia", "region": "Attica"},
        {"city": "Aspropyrgos", "region": "Attica"},
        {"city": "Corinth", "region": "Peloponnese"},
        {"city": "Gerakas", "region": "Attica"},
        {"city": "Metamorfosi", "region": "Attica"},
        {"city": "Giannitsa", "region": "Central Macedonia"},
        {"city": "Voula", "region": "Attica"},
        {"city": "Kamatero", "region": "Attica"},
        {"city": "Mytilene", "region": "North Aegean"},
        {"city": "Neapoli", "region": "Central Macedonia"},
        {"city": "Eleftherio-Kordelio", "region": "Central Macedonia"},
        {"city": "Chios", "region": "North Aegean"},
        {"city": "Agia Varvara", "region": "Attica"},
        {"city": "Kaisariani", "region": "Attica"},
        {"city": "Nea Filadelfeia", "region": "Attica"},
        {"city": "Moschato", "region": "Attica"},
        {"city": "Perama", "region": "Attica"},
        {"city": "Salamina", "region": "Attica"},
        {"city": "Eleusis", "region": "Attica"},
        {"city": "Corfu", "region": "Ionian Islands"},
        {"city": "Pyrgos", "region": "Western Greece"},
        {"city": "Megara", "region": "Attica"},
        {"city": "Kilkis", "region": "Central Macedonia"},
        {"city": "Dafni", "region": "Attica"},
        {"city": "Thebes", "region": "Central Greece"},
        {"city": "Melissia", "region": "Attica"},
        {"city": "Argos", "region": "Peloponnese"},
        {"city": "Arta", "region": "Epirus"},
        {"city": "Artemida", "region": "Attica"},
        {"city": "Livadeia", "region": "Central Greece"},
        {"city": "Pefki", "region": "Attica"},
        {"city": "Oraiokastro", "region": "Central Macedonia"},
        {"city": "Aigio", "region": "Western Greece"},
        {"city": "Kos", "region": "South Aegean"},
        {"city": "Koropi", "region": "Attica"},
        {"city": "Preveza", "region": "Epirus"},
        {"city": "Naousa", "region": "Central Macedonia"},
        {"city": "Orestiada", "region": "Eastern Macedonia and Thrace"},
        {"city": "Peraia", "region": "Central Macedonia"},
        {"city": "Edessa", "region": "Central Macedonia"},
        {"city": "Florina", "region": "Western Macedonia"},
        {"city": "Panorama", "region": "Central Macedonia"},
        {"city": "Nea Erythraia", "region": "Attica"},
        {"city": "Elliniko", "region": "Attica"},
        {"city": "Amaliada", "region": "Western Greece"},
        {"city": "Pallini", "region": "Attica"},
        {"city": "Sparta", "region": "Peloponnese"},
        {"city": "Agios Ioannis Rentis", "region": "Attica"},
        {"city": "Thermi", "region": "Central Macedonia"},
        {"city": "Vari", "region": "Attica"},
        {"city": "Nea Makri", "region": "Attica"},
        {"city": "Tavros", "region": "Attica"},
        {"city": "Alexandreia", "region": "Central Macedonia"},
        {"city": "Menemeni", "region": "Central Macedonia"},
        {"city": "Paiania", "region": "Attica"},
        {"city": "Kalyvia Thorikou", "region": "Attica"},
        {"city": "Nafplio", "region": "Peloponnese"},
        {"city": "Drapetsona", "region": "Attica"},
        {"city": "Efkarpia", "region": "Central Macedonia"},
        {"city": "Papagou", "region": "Attica"},
        {"city": "Nafpaktos", "region": "Western Greece"},
        {"city": "Kastoria", "region": "Δυτική Μακεδονία"},
        {"city": "Grevena", "region": "Δυτική Μακεδονία"},
        {"city": "Pefka", "region": "Central Macedonia"},
        {"city": "Nea Alikarnassos", "region": "Crete"},
        {"city": "Messolonghi", "region": "Western Greece"},
        {"city": "Gazi", "region": "Crete"},
        {"city": "Ierapetra", "region": "Crete"},
        {"city": "Kalymnos", "region": "South Aegean"},
        {"city": "Rafina", "region": "Attica"},
        {"city": "Loutraki", "region": "Peloponnese"},
        {"city": "Agios Nikolaos", "region": "Crete"},
        {"city": "Ermoupoli", "region": "South Aegean"},
        {"city": "Ialysos", "region": "South Aegean"},
        {"city": "Mandra", "region": "Attica"},
        {"city": "Tyrnavos", "region": "Thessaly"},
        {"city": "Glyka Nera", "region": "Attica"},
        {"city": "Ymittos", "region": "Attica"},
        {"city": "Neo Psychiko", "region": "Attica"}
    ],
    "gr": [
        {"city": "Αθληνα", "region": "Αττική"},
        {"city": "Θεσσαλονίκη", "region": "Κεντρική Μακεδονία"},
        {"city": "Πάτρα", "region": "Δυτική Ελλάδα"},
        {"city": "Πειραιάς", "region": "Αττική"},
        {"city": "Λάρισσα", "region": "Θεσσαλία"},
        {"city": "Ηράκλειο", "region": "Κρήτη"},
        {"city": "Περιστέρι", "region": "Αττική"},
        {"city": "Καλλίθεα", "region": "Αττική"},
        {"city": "Αχαρνές", "region": "Αττική"},
        {"city": "Καλαμαριά", "region": "Κεντρική Μακεδονία"},
        {"city": "Νίκαια", "region": "Αττική"},
        {"city": "Φλυφάδα", "region": "Αττική"},
        {"city": "Βόλος", "region": "Θεσσαλία"},
        {"city": "Ίλιο", "region": "Αττική"},
        {"city": "Ηλιούπολη", "region": "Αττική"},
        {"city": "Κερατσίνι", "region": "Αττική"},
        {"city": "Εύοσμος", "region": "Κεντρική Μακεδονία"},
        {"city": "Χαλάνδρι", "region": "Αττική"},
        {"city": "Νεα Σμύρνη", "region": "Αττική"},
        {"city": "Μαρούσι", "region": "Αττική"},
        {"city": "Άγιος Δημήτριος", "region": "Αττική"},
        {"city": "Ζωγράφου", "region": "Αττική"},
        {"city": "Αιγάλεω", "region": "Αττική"},
        {"city": "Νεα Ιωνία", "region": "Αττική"},
        {"city": "Ιωάννινα", "region": "Ηπειρός"},
        {"city": "Παλαίο Φάληρο", "region": "Αττική"},
        {"city": "Κορύδαλλος", "region": "Αττική"},
        {"city": "Τρίκαλα", "region": "Θεσσαλία"},
        {"city": "Βύρωνας", "region": "Αττική"},
        {"city": "Αγία Παρασκευή", "region": "Αττική"},
        {"city": "Γαλάτσι", "region": "Αττική"},
        {"city": "Αγρίνιο", "region": "Δυτική Ελλάδα"},
        {"city": "Χαλκίδα", "region": "Κεντρική Ελλάδα"},
        {"city": "Πετρούπολη", "region": "Αττική"},
        {"city": "Σέρρες", "region": "Κεντρική Μακεδονία"},
        {"city": "Αλεξανδρούπολη", "region": "Ανατολίκη Μακεδόνια και Θράκη"},
        {"city": "Ξάνθη", "region": "Ανατολίκη Μακεδόνια και Θράκη"},
        {"city": "Κατερίνη", "region": "Κεντρική Μακεδονία"},
        {"city": "Καλαμάτα", "region": "Πελοποννήσος"},
        {"city": "Καβάλα", "region": "Ανατολίκη Μακεδόνια και Θράκη"},
        {"city": "Χανιά", "region": "Κρήτη"},
        {"city": "Λαμία", "region": "Κεντρική Ελλάδα"},
        {"city": "Κομοτηνή", "region": "Ανατολίκη Μακεδόνια και Θράκη"},
        {"city": "Ηράκλειο", "region": "Αττική"},
        {"city": "Ρόδος", "region": "Νότιο Αιγαίο"},
        {"city": "Κηφισιά", "region": "Αττική"},
        {"city": "Σταυρούπολη", "region": "Κεντρική Μακεδονία"},
        {"city": "Χαϊδάρι", "region": "Αττική"},
        {"city": "Δράμα", "region": "Ανατολίκη Μακεδόνια και Θράκη"},
        {"city": "Βέροια", "region": "Κεντρική Μακεδονία"},
        {"city": "Άλιμος", "region": "Αττική"},
        {"city": "Κοζάνη", "region": "Δυτική Μακεδονία"},
        {"city": "Πολίχνη", "region": "Κεντρική Μακεδονία"},
        {"city": "Καρδίτσα", "region": "Θεσσαλία"},
        {"city": "Συκιές", "region": "Κεντρική Μακεδονία"},
        {"city": "Αμπελόκηποι", "region": "Κεντρική Μακεδονία"},
        {"city": "Πυλαία", "region": "Κεντρική Μακεδονία"},
        {"city": "Άγιοι Ανάργυροι", "region": "Αττική"},
        {"city": "Άνω Λιόσια", "region": "Αττική"},
        {"city": "Νεα Ιωνία", "region": "Θεσσαλία"},
        {"city": "Ρέθυμνο", "region": "Κρήτη"},
        {"city": "Πτολεμαΐδα", "region": "Δυτική Μακεδονία"},
        {"city": "Τρίπολη", "region": "Πελοποννήσος"},
        {"city": "Χολαργός", "region": "Αττική"},
        {"city": "Βριλήσσια", "region": "Αττική"},
        {"city": "Ασπροπυργός", "region": "Αττική"},
        {"city": "Κόρινθος", "region": "Πελοποννήσος"},
        {"city": "Γέρακας", "region": "Αττική"},
        {"city": "Μεταμόρφωση", "region": "Αττική"},
        {"city": "Γιαννιτσά", "region": "Κεντρική Μακεδονία"},
        {"city": "Βούλα", "region": "Αττική"},
        {"city": "Καματερό", "region": "Αττική"},
        {"city": "Μυτιλήνη", "region": "North Aegean"},
        {"city": "Νεάπολη", "region": "Κεντρική Μακεδονία"},
        {"city": "Ελευθέριο-Κορδελιό", "region": "Κεντρική Μακεδονία"},
        {"city": "Χίος", "region": "North Aegean"},
        {"city": "Αγία Βαρβάρα", "region": "Αττική"},
        {"city": "Καισαριάνη", "region": "Αττική"},
        {"city": "Νέα Φιλαδέλφεια", "region": "Αττική"},
        {"city": "Μοσχάτο", "region": "Αττική"},
        {"city": "Πέραμα", "region": "Αττική"},
        {"city": "Σαλαμίνα", "region": "Αττική"},
        {"city": "Ελευσίνα", "region": "Αττική"},
        {"city": "Κέρκυρα", "region": "Ionian Islands"},
        {"city": "Πύργος", "region": "Δυτική Ελλάδα"},
        {"city": "Μέγαρα", "region": "Αττική"},
        {"city": "Κιλκίς", "region": "Κεντρική Μακεδονία"},
        {"city": "Δάφνη", "region": "Αττική"},
        {"city": "Θήβα", "region": "Κεντρική Ελλάδα"},
        {"city": "Μελίσσια", "region": "Αττική"},
        {"city": "Άργος", "region": "Πελοποννήσος"},
        {"city": "Άρτα", "region": "Ηπειρός"},
        {"city": "Αρτέμιδα", "region": "Αττική"},
        {"city": "Λιβαδειά", "region": "Κεντρική Ελλάδα"},
        {"city": "Πεύκη", "region": "Αττική"},
        {"city": "Ωραιοκάστρο", "region": "Κεντρική Μακεδονία"},
        {"city": "Αίγιο", "region": "Δυτική Ελλάδα"},
        {"city": "Κώς", "region": "Νότιο Αιγαίο"},
        {"city": "Κορώπι", "region": "Αττική"},
        {"city": "Πρέβεζα", "region": "Ηπειρός"},
        {"city": "Νάουσα", "region": "Κεντρική Μακεδονία"},
        {"city": "Ορεστιάδα", "region": "Ανατολίκη Μακεδόνια και Θράκη"},
        {"city": "Πιερία", "region": "Κεντρική Μακεδονία"},
        {"city": "Έδεσσα", "region": "Κεντρική Μακεδονία"},
        {"city": "Φλώρινα", "region": "Δυτική Μακεδονία"},
        {"city": "Πανόραμα", "region": "Κεντρική Μακεδονία"},
        {"city": "Νέα Ερυθραία", "region": "Αττική"},
        {"city": "Ελληνικό", "region": "Αττική"},
        {"city": "Αμαλιάδα", "region": "Δυτική Ελλάδα"},
        {"city": "Παλλήνη", "region": "Αττική"},
        {"city": "Σπάρτη", "region": "Πελοποννήσος"},
        {"city": "Άγιος Ιωάννης Ρέντης", "region": "Αττική"},
        {"city": "Θέρμη", "region": "Κεντρική Μακεδονία"},
        {"city": "Βάρη", "region": "Αττική"},
        {"city": "Νέα Μακρη", "region": "Αττική"},
        {"city": "Ταύρος", "region": "Αττική"},
        {"city": "Αλεξάνδρεια", "region": "Κεντρική Μακεδονία"},
        {"city": "Μενεμένη", "region": "Κεντρική Μακεδονία"},
        {"city": "Παιανία", "region": "Αττική"},
        {"city": "Καλύβια Θορικού", "region": "Αττική"},
        {"city": "Ναύπλιο", "region": "Πελοποννήσος"},
        {"city": "Δραπετσώνα", "region": "Αττική"},
        {"city": "Ευκαρπία", "region": "Κεντρική Μακεδονία"},
        {"city": "Παπάγου", "region": "Αττική"},
        {"city": "Ναύπακτος", "region": "Δυτική Ελλάδα"},
        {"city": "Καστοριά", "region": "Δυτική Μακεδονία"},
        {"city": "Γεβενά", "region": "Δυτική Μακεδονία"},
        {"city": "Πεύκα", "region": "Κεντρική Μακεδονία"},
        {"city": "Νέα Αλικαρνασσός", "region": "Κρήτη"},
        {"city": "Μεσολόγγι", "region": "Δυτική Ελλάδα"},
        {"city": "Γάζι", "region": "Κρήτη"},
        {"city": "Ιεράπετρα", "region": "Κρήτη"},
        {"city": "Κάλυμνος", "region": "Νότιο Αιγαίο"},
        {"city": "Ραφήνα", "region": "Αττική"},
        {"city": "Λουτράκι", "region": "Πελοποννήσος"},
        {"city": "Άγιος Νικόλαος", "region": "Κρήτη"},
        {"city": "Ερμουπολή", "region": "Νότιο Αιγαίο"},
        {"city": "Ιαλυσός", "region": "Νότιο Αιγαίο"},
        {"city": "Μάνδρα", "region": "Αττική"},
        {"city": "Τύρναβος", "region": "Θεσσαλία"},
        {"city": "Γλυκά Νερά", "region": "Αττική"},
        {"city": "Υμηττός", "region": "Αττική"},
        {"city": "Νέο Ψυχικό", "region": "Αττική"}
    ]
}